miniparser.py
miniparser-0.0.8.dist-info/LICENSE
miniparser-0.0.8.dist-info/METADATA
miniparser-0.0.8.dist-info/WHEEL
miniparser-0.0.8.dist-info/top_level.txt
miniparser-0.0.8.dist-info/RECORD
